{
  "frame": "sdf/world coordinates, meters",
  "cones": [
    {
      "name": "cone_right1",
      "type": "yellow",
      "x": -0.0,
      "y": 1.6500000000000004,
      "z": 0.0,
      "roll": 0.0,
      "pitch": 0.0,
      "yaw": 0.0
    },
    {
      "name": "cone_right2",
      "type": "yellow",
      "x": -2.860558656929046,
      "y": 2.2190004944781316,
      "z": 0.0,
      "roll": 0.0,
      "pitch": 0.0,
      "yaw": 0.0
    },
    {
      "name": "cone_right3",
      "type": "yellow",
      "x": -5.285623189369442,
      "y": 3.839376810630557,
      "z": 0.0,
      "roll": 0.0,
      "pitch": 0.0,
      "yaw": 0.0
    },
    {
      "name": "cone_right4",
      "type": "yellow",
      "x": -6.905999505521868,
      "y": 6.264441343070954,
      "z": 0.0,
      "roll": 0.0,
      "pitch": 0.0,
      "yaw": 0.0
    },
    {
      "name": "cone_right5",
      "type": "yellow",
      "x": -7.475,
      "y": 9.125,
      "z": 0.0,
      "roll": 0.0,
      "pitch": 0.0,
      "yaw": 0.0
    },
    {
      "name": "cone_right6",
      "type": "yellow",
      "x": -6.905999505521868,
      "y": 11.985558656929046,
      "z": 0.0,
      "roll": 0.0,
      "pitch": 0.0,
      "yaw": 0.0
    },
    {
      "name": "cone_right7",
      "type": "yellow",
      "x": -5.285623189369443,
      "y": 14.410623189369442,
      "z": 0.0,
      "roll": 0.0,
      "pitch": 0.0,
      "yaw": 0.0
    },
    {
      "name": "cone_right8",
      "type": "yellow",
      "x": -2.860558656929047,
      "y": 16.03099950552187,
      "z": 0.0,
      "roll": 0.0,
      "pitch": 0.0,
      "yaw": 0.0
    },
    {
      "name": "cone_right9",
      "type": "yellow",
      "x": -9.154234823626465e-16,
      "y": 16.6,
      "z": 0.0,
      "roll": 0.0,
      "pitch": 0.0,
      "yaw": 0.0
    },
    {
      "name": "cone_right10",
      "type": "yellow",
      "x": 2.860558656929045,
      "y": 16.03099950552187,
      "z": 0.0,
      "roll": 0.0,
      "pitch": 0.0,
      "yaw": 0.0
    },
    {
      "name": "cone_right11",
      "type": "yellow",
      "x": 5.285623189369442,
      "y": 14.410623189369444,
      "z": 0.0,
      "roll": 0.0,
      "pitch": 0.0,
      "yaw": 0.0
    },
    {
      "name": "cone_right12",
      "type": "yellow",
      "x": 6.905999505521867,
      "y": 11.98555865692905,
      "z": 0.0,
      "roll": 0.0,
      "pitch": 0.0,
      "yaw": 0.0
    },
    {
      "name": "cone_right13",
      "type": "yellow",
      "x": 7.475,
      "y": 9.125000000000002,
      "z": 0.0,
      "roll": 0.0,
      "pitch": 0.0,
      "yaw": 0.0
    },
    {
      "name": "cone_right14",
      "type": "yellow",
      "x": 6.9059995055218675,
      "y": 6.264441343070953,
      "z": 0.0,
      "roll": 0.0,
      "pitch": 0.0,
      "yaw": 0.0
    },
    {
      "name": "cone_right15",
      "type": "yellow",
      "x": 5.285623189369444,
      "y": 3.839376810630559,
      "z": 0.0,
      "roll": 0.0,
      "pitch": 0.0,
      "yaw": 0.0
    },
    {
      "name": "cone_right16",
      "type": "yellow",
      "x": 2.8605586569290504,
      "y": 2.2190004944781334,
      "z": 0.0,
      "roll": 0.0,
      "pitch": 0.0,
      "yaw": 0.0
    },
    {
      "name": "cone_right17",
      "type": "yellow",
      "x": 7.619075567285049,
      "y": -1.5059244327149495,
      "z": 0.0,
      "roll": 0.0,
      "pitch": 0.0,
      "yaw": 0.0
    },
    {
      "name": "cone_right18",
      "type": "yellow",
      "x": 9.954801962809116,
      "y": -5.001586016266157,
      "z": 0.0,
      "roll": 0.0,
      "pitch": 0.0,
      "yaw": 0.0
    },
    {
      "name": "cone_right19",
      "type": "yellow",
      "x": 10.775,
      "y": -9.125,
      "z": 0.0,
      "roll": 0.0,
      "pitch": 0.0,
      "yaw": 0.0
    },
    {
      "name": "cone_right20",
      "type": "yellow",
      "x": 9.954801962809116,
      "y": -13.248413983733842,
      "z": 0.0,
      "roll": 0.0,
      "pitch": 0.0,
      "yaw": 0.0
    },
    {
      "name": "cone_right21",
      "type": "yellow",
      "x": 7.6190755672850505,
      "y": -16.744075567285048,
      "z": 0.0,
      "roll": 0.0,
      "pitch": 0.0,
      "yaw": 0.0
    },
    {
      "name": "cone_right22",
      "type": "yellow",
      "x": 4.123413983733844,
      "y": -19.079801962809114,
      "z": 0.0,
      "roll": 0.0,
      "pitch": 0.0,
      "yaw": 0.0
    },
    {
      "name": "cone_right23",
      "type": "yellow",
      "x": 1.3195569260812732e-15,
      "y": -19.9,
      "z": 0.0,
      "roll": 0.0,
      "pitch": 0.0,
      "yaw": 0.0
    },
    {
      "name": "cone_right24",
      "type": "yellow",
      "x": -4.123413983733841,
      "y": -19.079801962809114,
      "z": 0.0,
      "roll": 0.0,
      "pitch": 0.0,
      "yaw": 0.0
    },
    {
      "name": "cone_right25",
      "type": "yellow",
      "x": -7.619075567285049,
      "y": -16.74407556728505,
      "z": 0.0,
      "roll": 0.0,
      "pitch": 0.0,
      "yaw": 0.0
    },
    {
      "name": "cone_right26",
      "type": "yellow",
      "x": -9.954801962809112,
      "y": -13.248413983733847,
      "z": 0.0,
      "roll": 0.0,
      "pitch": 0.0,
      "yaw": 0.0
    },
    {
      "name": "cone_right27",
      "type": "yellow",
      "x": -10.775,
      "y": -9.125000000000002,
      "z": 0.0,
      "roll": 0.0,
      "pitch": 0.0,
      "yaw": 0.0
    },
    {
      "name": "cone_right28",
      "type": "yellow",
      "x": -9.954801962809114,
      "y": -5.001586016266155,
      "z": 0.0,
      "roll": 0.0,
      "pitch": 0.0,
      "yaw": 0.0
    },
    {
      "name": "cone_right29",
      "type": "yellow",
      "x": -7.619075567285051,
      "y": -1.5059244327149521,
      "z": 0.0,
      "roll": 0.0,
      "pitch": 0.0,
      "yaw": 0.0
    },
    {
      "name": "cone_left1",
      "type": "blue",
      "x": -7.619075567285049,
      "y": 1.5059244327149495,
      "z": 0.0,
      "roll": 0.0,
      "pitch": 0.0,
      "yaw": 0.0
    },
    {
      "name": "cone_left2",
      "type": "blue",
      "x": -9.954801962809116,
      "y": 5.001586016266157,
      "z": 0.0,
      "roll": 0.0,
      "pitch": 0.0,
      "yaw": 0.0
    },
    {
      "name": "cone_left3",
      "type": "blue",
      "x": -10.775,
      "y": 9.125,
      "z": 0.0,
      "roll": 0.0,
      "pitch": 0.0,
      "yaw": 0.0
    },
    {
      "name": "cone_left4",
      "type": "blue",
      "x": -9.954801962809116,
      "y": 13.248413983733842,
      "z": 0.0,
      "roll": 0.0,
      "pitch": 0.0,
      "yaw": 0.0
    },
    {
      "name": "cone_left5",
      "type": "blue",
      "x": -7.6190755672850505,
      "y": 16.744075567285048,
      "z": 0.0,
      "roll": 0.0,
      "pitch": 0.0,
      "yaw": 0.0
    },
    {
      "name": "cone_left6",
      "type": "blue",
      "x": -4.123413983733844,
      "y": 19.079801962809114,
      "z": 0.0,
      "roll": 0.0,
      "pitch": 0.0,
      "yaw": 0.0
    },
    {
      "name": "cone_left7",
      "type": "blue",
      "x": -1.3195569260812732e-15,
      "y": 19.9,
      "z": 0.0,
      "roll": 0.0,
      "pitch": 0.0,
      "yaw": 0.0
    },
    {
      "name": "cone_left8",
      "type": "blue",
      "x": 4.123413983733841,
      "y": 19.079801962809114,
      "z": 0.0,
      "roll": 0.0,
      "pitch": 0.0,
      "yaw": 0.0
    },
    {
      "name": "cone_left9",
      "type": "blue",
      "x": 7.619075567285049,
      "y": 16.74407556728505,
      "z": 0.0,
      "roll": 0.0,
      "pitch": 0.0,
      "yaw": 0.0
    },
    {
      "name": "cone_left10",
      "type": "blue",
      "x": 9.954801962809112,
      "y": 13.248413983733847,
      "z": 0.0,
      "roll": 0.0,
      "pitch": 0.0,
      "yaw": 0.0
    },
    {
      "name": "cone_left11",
      "type": "blue",
      "x": 10.775,
      "y": 9.125000000000002,
      "z": 0.0,
      "roll": 0.0,
      "pitch": 0.0,
      "yaw": 0.0
    },
    {
      "name": "cone_left12",
      "type": "blue",
      "x": 9.954801962809114,
      "y": 5.001586016266155,
      "z": 0.0,
      "roll": 0.0,
      "pitch": 0.0,
      "yaw": 0.0
    },
    {
      "name": "cone_left13",
      "type": "blue",
      "x": 7.619075567285051,
      "y": 1.5059244327149521,
      "z": 0.0,
      "roll": 0.0,
      "pitch": 0.0,
      "yaw": 0.0
    },
    {
      "name": "cone_left14",
      "type": "blue",
      "x": 0.0,
      "y": -1.6500000000000004,
      "z": 0.0,
      "roll": 0.0,
      "pitch": 0.0,
      "yaw": 0.0
    },
    {
      "name": "cone_left15",
      "type": "blue",
      "x": 2.860558656929046,
      "y": -2.2190004944781316,
      "z": 0.0,
      "roll": 0.0,
      "pitch": 0.0,
      "yaw": 0.0
    },
    {
      "name": "cone_left16",
      "type": "blue",
      "x": 5.285623189369442,
      "y": -3.839376810630557,
      "z": 0.0,
      "roll": 0.0,
      "pitch": 0.0,
      "yaw": 0.0
    },
    {
      "name": "cone_left17",
      "type": "blue",
      "x": 6.905999505521868,
      "y": -6.264441343070954,
      "z": 0.0,
      "roll": 0.0,
      "pitch": 0.0,
      "yaw": 0.0
    },
    {
      "name": "cone_left18",
      "type": "blue",
      "x": 7.475,
      "y": -9.125,
      "z": 0.0,
      "roll": 0.0,
      "pitch": 0.0,
      "yaw": 0.0
    },
    {
      "name": "cone_left19",
      "type": "blue",
      "x": 6.905999505521868,
      "y": -11.985558656929046,
      "z": 0.0,
      "roll": 0.0,
      "pitch": 0.0,
      "yaw": 0.0
    },
    {
      "name": "cone_left20",
      "type": "blue",
      "x": 5.285623189369443,
      "y": -14.410623189369442,
      "z": 0.0,
      "roll": 0.0,
      "pitch": 0.0,
      "yaw": 0.0
    },
    {
      "name": "cone_left21",
      "type": "blue",
      "x": 2.860558656929047,
      "y": -16.03099950552187,
      "z": 0.0,
      "roll": 0.0,
      "pitch": 0.0,
      "yaw": 0.0
    },
    {
      "name": "cone_left22",
      "type": "blue",
      "x": 9.154234823626465e-16,
      "y": -16.6,
      "z": 0.0,
      "roll": 0.0,
      "pitch": 0.0,
      "yaw": 0.0
    },
    {
      "name": "cone_left23",
      "type": "blue",
      "x": -2.860558656929045,
      "y": -16.03099950552187,
      "z": 0.0,
      "roll": 0.0,
      "pitch": 0.0,
      "yaw": 0.0
    },
    {
      "name": "cone_left24",
      "type": "blue",
      "x": -5.285623189369442,
      "y": -14.410623189369444,
      "z": 0.0,
      "roll": 0.0,
      "pitch": 0.0,
      "yaw": 0.0
    },
    {
      "name": "cone_left25",
      "type": "blue",
      "x": -6.905999505521867,
      "y": -11.98555865692905,
      "z": 0.0,
      "roll": 0.0,
      "pitch": 0.0,
      "yaw": 0.0
    },
    {
      "name": "cone_left26",
      "type": "blue",
      "x": -7.475,
      "y": -9.125000000000002,
      "z": 0.0,
      "roll": 0.0,
      "pitch": 0.0,
      "yaw": 0.0
    },
    {
      "name": "cone_left27",
      "type": "blue",
      "x": -6.9059995055218675,
      "y": -6.264441343070953,
      "z": 0.0,
      "roll": 0.0,
      "pitch": 0.0,
      "yaw": 0.0
    },
    {
      "name": "cone_left28",
      "type": "blue",
      "x": -5.285623189369444,
      "y": -3.839376810630559,
      "z": 0.0,
      "roll": 0.0,
      "pitch": 0.0,
      "yaw": 0.0
    },
    {
      "name": "cone_left29",
      "type": "blue",
      "x": -2.8605586569290504,
      "y": -2.2190004944781334,
      "z": 0.0,
      "roll": 0.0,
      "pitch": 0.0,
      "yaw": 0.0
    },
    {
      "name": "cone_orange1",
      "type": "orange",
      "x": -11.25,
      "y": 1.65,
      "z": 0.0,
      "roll": 0.0,
      "pitch": 0.0,
      "yaw": 0.0
    },
    {
      "name": "cone_orange2",
      "type": "orange",
      "x": -11.25,
      "y": -1.65,
      "z": 0.0,
      "roll": 0.0,
      "pitch": 0.0,
      "yaw": 0.0
    },
    {
      "name": "cone_orange3",
      "type": "orange",
      "x": -15.0,
      "y": 1.65,
      "z": 0.0,
      "roll": 0.0,
      "pitch": 0.0,
      "yaw": 0.0
    },
    {
      "name": "cone_orange4",
      "type": "orange",
      "x": -15.0,
      "y": -1.65,
      "z": 0.0,
      "roll": 0.0,
      "pitch": 0.0,
      "yaw": 0.0
    },
    {
      "name": "cone_orange5",
      "type": "orange",
      "x": 11.0,
      "y": 1.65,
      "z": 0.0,
      "roll": 0.0,
      "pitch": 0.0,
      "yaw": 0.0
    },
    {
      "name": "cone_orange6",
      "type": "orange",
      "x": 11.0,
      "y": -1.65,
      "z": 0.0,
      "roll": 0.0,
      "pitch": 0.0,
      "yaw": 0.0
    },
    {
      "name": "cone_orange7",
      "type": "orange",
      "x": 16.0,
      "y": 1.65,
      "z": 0.0,
      "roll": 0.0,
      "pitch": 0.0,
      "yaw": 0.0
    },
    {
      "name": "cone_orange8",
      "type": "orange",
      "x": 16.0,
      "y": -1.65,
      "z": 0.0,
      "roll": 0.0,
      "pitch": 0.0,
      "yaw": 0.0
    },
    {
      "name": "cone_orange9",
      "type": "orange",
      "x": 21.0,
      "y": 1.65,
      "z": 0.0,
      "roll": 0.0,
      "pitch": 0.0,
      "yaw": 0.0
    },
    {
      "name": "cone_orange10",
      "type": "orange",
      "x": 21.0,
      "y": -1.65,
      "z": 0.0,
      "roll": 0.0,
      "pitch": 0.0,
      "yaw": 0.0
    },
    {
      "name": "cone_orange11",
      "type": "orange",
      "x": 21.0,
      "y": 0.0,
      "z": 0.0,
      "roll": 0.0,
      "pitch": 0.0,
      "yaw": 0.0
    },
    {
      "name": "cone_orange12",
      "type": "orange",
      "x": 21.0,
      "y": 1.65,
      "z": 0.0,
      "roll": 0.0,
      "pitch": 0.0,
      "yaw": 0.0
    },
    {
      "name": "cone_orange_big1",
      "type": "orange_big",
      "x": -1.3,
      "y": 2.0,
      "z": 0.0,
      "roll": 0.0,
      "pitch": 0.0,
      "yaw": 0.0
    },
    {
      "name": "cone_orange_big2",
      "type": "orange_big",
      "x": -1.3,
      "y": -2.0,
      "z": 0.0,
      "roll": 0.0,
      "pitch": 0.0,
      "yaw": 0.0
    },
    {
      "name": "cone_orange_big3",
      "type": "orange_big",
      "x": 1.3,
      "y": 2.0,
      "z": 0.0,
      "roll": 0.0,
      "pitch": 0.0,
      "yaw": 0.0
    },
    {
      "name": "cone_orange_big4",
      "type": "orange_big",
      "x": 1.3,
      "y": -2.0,
      "z": 0.0,
      "roll": 0.0,
      "pitch": 0.0,
      "yaw": 0.0
    }
  ]
}